gptutil/__init__.py
gptutil/ask.py
gptutil/chat.py
gptutil/image.py
gptutil/interact.py
gptutil/agent/__init__.py
gptutil/agent/code.py
gptutil/example/assistant.yaml
gptutil/example/snippet.yaml
gptutil-0.1.6.dist-info/LICENSE
gptutil-0.1.6.dist-info/METADATA
gptutil-0.1.6.dist-info/WHEEL
gptutil-0.1.6.dist-info/entry_points.txt
gptutil-0.1.6.dist-info/top_level.txt
gptutil-0.1.6.dist-info/RECORD
